mangomango/__init__.py
mangomango-0.1.3.dist-info/METADATA
mangomango-0.1.3.dist-info/WHEEL
mangomango-0.1.3.dist-info/RECORD
