Metadata-Version: 2.3
Name: mangomango
Version: 0.1.3
Summary: A simple MongoDB client that works with Pydantic models.
Author: Izak
Author-email: frdev.izak@gmail.com
Requires-Python: >=3.12
Classifier: Programming Language :: Python :: 3
Classifier: Programming Language :: Python :: 3.12
Classifier: Programming Language :: Python :: 3.13
Requires-Dist: pydantic (>=2.10.4,<3.0.0)
Requires-Dist: pymongo (>=4.10.1,<5.0.0)
Requires-Dist: rich (>=13.9.4,<14.0.0)
